[
{
    "arguments": [
        "clang",
        "-I",
        "C:\\Qt\\Tools\\QtCreator\\share\\qtcreator\\cplusplus\\wrappedMingwHeaders",
        "-I",
        "C:\\Qt\\Tools\\QtCreator\\share\\qtcreator\\cplusplus\\wrappedQtHeaders",
        "-I",
        "C:\\Qt\\Tools\\QtCreator\\share\\qtcreator\\cplusplus\\wrappedQtHeaders\\QtCore",
        "-I",
        "C:\\Users\\Acer\\AppData\\Local\\Temp\\QtCreator-jcbynM\\clang-uiheader-sdQJfv",
        "-nostdinc",
        "-nostdinc++",
        "-g",
        "-std=gnu++17",
        "-fsyntax-only",
        "-m64",
        "--target=x86_64-w64-mingw32",
        "-DQ_CREATOR_RUN",
        "-DMINGW_HAS_SECURE_API",
        "-DQT_CORE_LIB",
        "-DQT_GUI_LIB",
        "-DQT_NEEDS_QMAIN",
        "-DQT_PRINTSUPPORT_LIB",
        "-DQT_WIDGETS_LIB",
        "-DUNICODE",
        "-DWIN32",
        "-DWIN64",
        "-D_ENABLE_EXTENDED_ALIGNED_STORAGE",
        "-D_UNICODE",
        "-D_WIN64",
        "-I",
        "D:\\multicpp\\build-Paint-Desktop_Qt_6_2_4_MinGW_64_bit-Debug",
        "-I",
        "D:\\multicpp\\Paint",
        "-I",
        "D:\\multicpp\\build-Paint-Desktop_Qt_6_2_4_MinGW_64_bit-Debug\\Paint_autogen\\include",
        "-I",
        "C:\\Qt\\6.2.4\\mingw_64\\include\\QtCore",
        "-I",
        "C:\\Qt\\6.2.4\\mingw_64\\include",
        "-I",
        "C:\\Qt\\6.2.4\\mingw_64\\mkspecs\\win32-g++",
        "-I",
        "C:\\Qt\\6.2.4\\mingw_64\\include\\QtWidgets",
        "-I",
        "C:\\Qt\\6.2.4\\mingw_64\\include\\QtGui",
        "-I",
        "C:\\Qt\\6.2.4\\mingw_64\\include\\QtPrintSupport",
        "-isystem",
        "C:\\Qt\\Tools\\mingw1120_64\\lib\\gcc\\x86_64-w64-mingw32\\11.2.0\\include\\c++",
        "-isystem",
        "C:\\Qt\\Tools\\mingw1120_64\\lib\\gcc\\x86_64-w64-mingw32\\11.2.0\\include\\c++\\x86_64-w64-mingw32",
        "-isystem",
        "C:\\Qt\\Tools\\mingw1120_64\\lib\\gcc\\x86_64-w64-mingw32\\11.2.0\\include\\c++\\backward",
        "-isystem",
        "C:\\Qt\\Tools\\QtCreator\\bin\\clang\\lib\\clang\\14.0.0\\include",
        "-isystem",
        "C:\\Qt\\Tools\\mingw1120_64\\x86_64-w64-mingw32\\include",
        "-fmessage-length=0",
        "-fdiagnostics-show-note-include-stack",
        "-fretain-comments-from-system-headers",
        "-fmacro-backtrace-limit=0",
        "-ferror-limit=1000",
        "-x",
        "c++",
        "-Wno-unknown-pragmas",
        "-Wno-unknown-warning-option",
        "-Wno-documentation-unknown-command",
        "-fno-delayed-template-parsing",
        "D:\\multicpp\\Paint\\main.cpp"
    ],
    "directory": "D:/multicpp/build-Paint-Desktop_Qt_6_2_4_MinGW_64_bit-Debug/.qtc_clangd",
    "file": "D:/multicpp/Paint/main.cpp"
},
{
    "arguments": [
        "clang",
        "-I",
        "C:\\Qt\\Tools\\QtCreator\\share\\qtcreator\\cplusplus\\wrappedMingwHeaders",
        "-I",
        "C:\\Qt\\Tools\\QtCreator\\share\\qtcreator\\cplusplus\\wrappedQtHeaders",
        "-I",
        "C:\\Qt\\Tools\\QtCreator\\share\\qtcreator\\cplusplus\\wrappedQtHeaders\\QtCore",
        "-I",
        "C:\\Users\\Acer\\AppData\\Local\\Temp\\QtCreator-jcbynM\\clang-uiheader-sdQJfv",
        "-nostdinc",
        "-nostdinc++",
        "-g",
        "-std=gnu++17",
        "-fsyntax-only",
        "-m64",
        "--target=x86_64-w64-mingw32",
        "-DQ_CREATOR_RUN",
        "-DMINGW_HAS_SECURE_API",
        "-DQT_CORE_LIB",
        "-DQT_GUI_LIB",
        "-DQT_NEEDS_QMAIN",
        "-DQT_PRINTSUPPORT_LIB",
        "-DQT_WIDGETS_LIB",
        "-DUNICODE",
        "-DWIN32",
        "-DWIN64",
        "-D_ENABLE_EXTENDED_ALIGNED_STORAGE",
        "-D_UNICODE",
        "-D_WIN64",
        "-I",
        "D:\\multicpp\\build-Paint-Desktop_Qt_6_2_4_MinGW_64_bit-Debug",
        "-I",
        "D:\\multicpp\\Paint",
        "-I",
        "D:\\multicpp\\build-Paint-Desktop_Qt_6_2_4_MinGW_64_bit-Debug\\Paint_autogen\\include",
        "-I",
        "C:\\Qt\\6.2.4\\mingw_64\\include\\QtCore",
        "-I",
        "C:\\Qt\\6.2.4\\mingw_64\\include",
        "-I",
        "C:\\Qt\\6.2.4\\mingw_64\\mkspecs\\win32-g++",
        "-I",
        "C:\\Qt\\6.2.4\\mingw_64\\include\\QtWidgets",
        "-I",
        "C:\\Qt\\6.2.4\\mingw_64\\include\\QtGui",
        "-I",
        "C:\\Qt\\6.2.4\\mingw_64\\include\\QtPrintSupport",
        "-isystem",
        "C:\\Qt\\Tools\\mingw1120_64\\lib\\gcc\\x86_64-w64-mingw32\\11.2.0\\include\\c++",
        "-isystem",
        "C:\\Qt\\Tools\\mingw1120_64\\lib\\gcc\\x86_64-w64-mingw32\\11.2.0\\include\\c++\\x86_64-w64-mingw32",
        "-isystem",
        "C:\\Qt\\Tools\\mingw1120_64\\lib\\gcc\\x86_64-w64-mingw32\\11.2.0\\include\\c++\\backward",
        "-isystem",
        "C:\\Qt\\Tools\\QtCreator\\bin\\clang\\lib\\clang\\14.0.0\\include",
        "-isystem",
        "C:\\Qt\\Tools\\mingw1120_64\\x86_64-w64-mingw32\\include",
        "-fmessage-length=0",
        "-fdiagnostics-show-note-include-stack",
        "-fretain-comments-from-system-headers",
        "-fmacro-backtrace-limit=0",
        "-ferror-limit=1000",
        "-x",
        "c++",
        "-Wno-unknown-pragmas",
        "-Wno-unknown-warning-option",
        "-Wno-documentation-unknown-command",
        "-fno-delayed-template-parsing",
        "D:\\multicpp\\Paint\\mainwindow.cpp"
    ],
    "directory": "D:/multicpp/build-Paint-Desktop_Qt_6_2_4_MinGW_64_bit-Debug/.qtc_clangd",
    "file": "D:/multicpp/Paint/mainwindow.cpp"
},
{
    "arguments": [
        "clang",
        "-I",
        "C:\\Qt\\Tools\\QtCreator\\share\\qtcreator\\cplusplus\\wrappedMingwHeaders",
        "-I",
        "C:\\Qt\\Tools\\QtCreator\\share\\qtcreator\\cplusplus\\wrappedQtHeaders",
        "-I",
        "C:\\Qt\\Tools\\QtCreator\\share\\qtcreator\\cplusplus\\wrappedQtHeaders\\QtCore",
        "-I",
        "C:\\Users\\Acer\\AppData\\Local\\Temp\\QtCreator-jcbynM\\clang-uiheader-sdQJfv",
        "-nostdinc",
        "-nostdinc++",
        "-g",
        "-std=gnu++17",
        "-fsyntax-only",
        "-m64",
        "--target=x86_64-w64-mingw32",
        "-DQ_CREATOR_RUN",
        "-DMINGW_HAS_SECURE_API",
        "-DQT_CORE_LIB",
        "-DQT_GUI_LIB",
        "-DQT_NEEDS_QMAIN",
        "-DQT_PRINTSUPPORT_LIB",
        "-DQT_WIDGETS_LIB",
        "-DUNICODE",
        "-DWIN32",
        "-DWIN64",
        "-D_ENABLE_EXTENDED_ALIGNED_STORAGE",
        "-D_UNICODE",
        "-D_WIN64",
        "-I",
        "D:\\multicpp\\build-Paint-Desktop_Qt_6_2_4_MinGW_64_bit-Debug",
        "-I",
        "D:\\multicpp\\Paint",
        "-I",
        "D:\\multicpp\\build-Paint-Desktop_Qt_6_2_4_MinGW_64_bit-Debug\\Paint_autogen\\include",
        "-I",
        "C:\\Qt\\6.2.4\\mingw_64\\include\\QtCore",
        "-I",
        "C:\\Qt\\6.2.4\\mingw_64\\include",
        "-I",
        "C:\\Qt\\6.2.4\\mingw_64\\mkspecs\\win32-g++",
        "-I",
        "C:\\Qt\\6.2.4\\mingw_64\\include\\QtWidgets",
        "-I",
        "C:\\Qt\\6.2.4\\mingw_64\\include\\QtGui",
        "-I",
        "C:\\Qt\\6.2.4\\mingw_64\\include\\QtPrintSupport",
        "-isystem",
        "C:\\Qt\\Tools\\mingw1120_64\\lib\\gcc\\x86_64-w64-mingw32\\11.2.0\\include\\c++",
        "-isystem",
        "C:\\Qt\\Tools\\mingw1120_64\\lib\\gcc\\x86_64-w64-mingw32\\11.2.0\\include\\c++\\x86_64-w64-mingw32",
        "-isystem",
        "C:\\Qt\\Tools\\mingw1120_64\\lib\\gcc\\x86_64-w64-mingw32\\11.2.0\\include\\c++\\backward",
        "-isystem",
        "C:\\Qt\\Tools\\QtCreator\\bin\\clang\\lib\\clang\\14.0.0\\include",
        "-isystem",
        "C:\\Qt\\Tools\\mingw1120_64\\x86_64-w64-mingw32\\include",
        "-fmessage-length=0",
        "-fdiagnostics-show-note-include-stack",
        "-fretain-comments-from-system-headers",
        "-fmacro-backtrace-limit=0",
        "-ferror-limit=1000",
        "-x",
        "c++",
        "-Wno-unknown-pragmas",
        "-Wno-unknown-warning-option",
        "-Wno-documentation-unknown-command",
        "-fno-delayed-template-parsing",
        "D:\\multicpp\\Paint\\scribblearea.cpp"
    ],
    "directory": "D:/multicpp/build-Paint-Desktop_Qt_6_2_4_MinGW_64_bit-Debug/.qtc_clangd",
    "file": "D:/multicpp/Paint/scribblearea.cpp"
},
{
    "arguments": [
        "clang",
        "-I",
        "C:\\Qt\\Tools\\QtCreator\\share\\qtcreator\\cplusplus\\wrappedMingwHeaders",
        "-I",
        "C:\\Qt\\Tools\\QtCreator\\share\\qtcreator\\cplusplus\\wrappedQtHeaders",
        "-I",
        "C:\\Qt\\Tools\\QtCreator\\share\\qtcreator\\cplusplus\\wrappedQtHeaders\\QtCore",
        "-I",
        "C:\\Users\\Acer\\AppData\\Local\\Temp\\QtCreator-jcbynM\\clang-uiheader-sdQJfv",
        "-nostdinc",
        "-nostdinc++",
        "-g",
        "-std=gnu++17",
        "-fsyntax-only",
        "-m64",
        "--target=x86_64-w64-mingw32",
        "-DQ_CREATOR_RUN",
        "-DMINGW_HAS_SECURE_API",
        "-DQT_CORE_LIB",
        "-DQT_GUI_LIB",
        "-DQT_NEEDS_QMAIN",
        "-DQT_PRINTSUPPORT_LIB",
        "-DQT_WIDGETS_LIB",
        "-DUNICODE",
        "-DWIN32",
        "-DWIN64",
        "-D_ENABLE_EXTENDED_ALIGNED_STORAGE",
        "-D_UNICODE",
        "-D_WIN64",
        "-I",
        "D:\\multicpp\\build-Paint-Desktop_Qt_6_2_4_MinGW_64_bit-Debug",
        "-I",
        "D:\\multicpp\\Paint",
        "-I",
        "D:\\multicpp\\build-Paint-Desktop_Qt_6_2_4_MinGW_64_bit-Debug\\Paint_autogen\\include",
        "-I",
        "C:\\Qt\\6.2.4\\mingw_64\\include\\QtCore",
        "-I",
        "C:\\Qt\\6.2.4\\mingw_64\\include",
        "-I",
        "C:\\Qt\\6.2.4\\mingw_64\\mkspecs\\win32-g++",
        "-I",
        "C:\\Qt\\6.2.4\\mingw_64\\include\\QtWidgets",
        "-I",
        "C:\\Qt\\6.2.4\\mingw_64\\include\\QtGui",
        "-I",
        "C:\\Qt\\6.2.4\\mingw_64\\include\\QtPrintSupport",
        "-isystem",
        "C:\\Qt\\Tools\\mingw1120_64\\lib\\gcc\\x86_64-w64-mingw32\\11.2.0\\include\\c++",
        "-isystem",
        "C:\\Qt\\Tools\\mingw1120_64\\lib\\gcc\\x86_64-w64-mingw32\\11.2.0\\include\\c++\\x86_64-w64-mingw32",
        "-isystem",
        "C:\\Qt\\Tools\\mingw1120_64\\lib\\gcc\\x86_64-w64-mingw32\\11.2.0\\include\\c++\\backward",
        "-isystem",
        "C:\\Qt\\Tools\\QtCreator\\bin\\clang\\lib\\clang\\14.0.0\\include",
        "-isystem",
        "C:\\Qt\\Tools\\mingw1120_64\\x86_64-w64-mingw32\\include",
        "-fmessage-length=0",
        "-fdiagnostics-show-note-include-stack",
        "-fretain-comments-from-system-headers",
        "-fmacro-backtrace-limit=0",
        "-ferror-limit=1000",
        "-x",
        "c++-header",
        "-Wno-unknown-pragmas",
        "-Wno-unknown-warning-option",
        "-Wno-documentation-unknown-command",
        "-fno-delayed-template-parsing",
        "D:\\multicpp\\Paint\\mainwindow.h"
    ],
    "directory": "D:/multicpp/build-Paint-Desktop_Qt_6_2_4_MinGW_64_bit-Debug/.qtc_clangd",
    "file": "D:/multicpp/Paint/mainwindow.h"
},
{
    "arguments": [
        "clang",
        "-I",
        "C:\\Qt\\Tools\\QtCreator\\share\\qtcreator\\cplusplus\\wrappedMingwHeaders",
        "-I",
        "C:\\Qt\\Tools\\QtCreator\\share\\qtcreator\\cplusplus\\wrappedQtHeaders",
        "-I",
        "C:\\Qt\\Tools\\QtCreator\\share\\qtcreator\\cplusplus\\wrappedQtHeaders\\QtCore",
        "-I",
        "C:\\Users\\Acer\\AppData\\Local\\Temp\\QtCreator-jcbynM\\clang-uiheader-sdQJfv",
        "-nostdinc",
        "-nostdinc++",
        "-g",
        "-std=gnu++17",
        "-fsyntax-only",
        "-m64",
        "--target=x86_64-w64-mingw32",
        "-DQ_CREATOR_RUN",
        "-DMINGW_HAS_SECURE_API",
        "-DQT_CORE_LIB",
        "-DQT_GUI_LIB",
        "-DQT_NEEDS_QMAIN",
        "-DQT_PRINTSUPPORT_LIB",
        "-DQT_WIDGETS_LIB",
        "-DUNICODE",
        "-DWIN32",
        "-DWIN64",
        "-D_ENABLE_EXTENDED_ALIGNED_STORAGE",
        "-D_UNICODE",
        "-D_WIN64",
        "-I",
        "D:\\multicpp\\build-Paint-Desktop_Qt_6_2_4_MinGW_64_bit-Debug",
        "-I",
        "D:\\multicpp\\Paint",
        "-I",
        "D:\\multicpp\\build-Paint-Desktop_Qt_6_2_4_MinGW_64_bit-Debug\\Paint_autogen\\include",
        "-I",
        "C:\\Qt\\6.2.4\\mingw_64\\include\\QtCore",
        "-I",
        "C:\\Qt\\6.2.4\\mingw_64\\include",
        "-I",
        "C:\\Qt\\6.2.4\\mingw_64\\mkspecs\\win32-g++",
        "-I",
        "C:\\Qt\\6.2.4\\mingw_64\\include\\QtWidgets",
        "-I",
        "C:\\Qt\\6.2.4\\mingw_64\\include\\QtGui",
        "-I",
        "C:\\Qt\\6.2.4\\mingw_64\\include\\QtPrintSupport",
        "-isystem",
        "C:\\Qt\\Tools\\mingw1120_64\\lib\\gcc\\x86_64-w64-mingw32\\11.2.0\\include\\c++",
        "-isystem",
        "C:\\Qt\\Tools\\mingw1120_64\\lib\\gcc\\x86_64-w64-mingw32\\11.2.0\\include\\c++\\x86_64-w64-mingw32",
        "-isystem",
        "C:\\Qt\\Tools\\mingw1120_64\\lib\\gcc\\x86_64-w64-mingw32\\11.2.0\\include\\c++\\backward",
        "-isystem",
        "C:\\Qt\\Tools\\QtCreator\\bin\\clang\\lib\\clang\\14.0.0\\include",
        "-isystem",
        "C:\\Qt\\Tools\\mingw1120_64\\x86_64-w64-mingw32\\include",
        "-fmessage-length=0",
        "-fdiagnostics-show-note-include-stack",
        "-fretain-comments-from-system-headers",
        "-fmacro-backtrace-limit=0",
        "-ferror-limit=1000",
        "-x",
        "c++-header",
        "-Wno-unknown-pragmas",
        "-Wno-unknown-warning-option",
        "-Wno-documentation-unknown-command",
        "-fno-delayed-template-parsing",
        "D:\\multicpp\\Paint\\scribble.h"
    ],
    "directory": "D:/multicpp/build-Paint-Desktop_Qt_6_2_4_MinGW_64_bit-Debug/.qtc_clangd",
    "file": "D:/multicpp/Paint/scribble.h"
}
]